[{"content":"九月的某一天，也许是八月。和家人通完电话后，我同往常一样照例陷入了对爱情的思考，这算是每次例行通话的课后作业。\n其间我想到村上春树一篇小说《遇见百分百女孩》，接着又想到塞林格的《破碎故事之心》，是两篇超短的小说。我打开手机重读一遍，很感动，仿佛是第一次读到。我还是十五年前那个文学青年。\n村上春树和塞林格我读的都不多，《挪威的森林》是读过的，不记得读完了没有，《麦田里的守望者》是去年才读的。我算不得一个合格的文学青年。我真正与“文学青年”沾边，是我的中学时代，我们学校那时候主办有一本季刊，面向全校师生征集文章的，我投过几次稿，也刊出过几次。整个中学时代我的阅读量不大，读的比较多的是古代传奇和现代诗。从课本里知道闻一多、徐志摩、北岛、流沙河、食指，开始读他们的诗，再学着写诗。诗歌的门槛是高的，但少年的心性更高。\n我并不是一个“文学青年”，更多的是“剽窃青年”。我没有什么写诗的天赋，所有的习作都是寻章摘句拼凑而成。我最受老师赞扬的一首诗是家里一本1998年的“诗歌年鉴”台历中抄来的，这首诗的题目叫“月亮，我们的家禽”1，里面的意象太有想象力了，我不得不抄。后来这首诗被全年级传阅的时候我诚惶诚恐。直到有一天一个姑娘带着我被传阅的作文本来找我，她说：你太有才华了。我冷静地答复：是。后面的聊天内容我已忘个干净，我只知道先前的惶恐已完全抛诸脑后，我决定继续抄下去，把读到的最美的诗都抄给她看。\n我短暂的文学青年史仿佛就此就断代，不知从什么时候开始，我不再写东西了。当然与“那个姑娘找我”的小插曲没有任何关系。渐渐的不写东西以后，“文学”似乎离我越来越远，虽然近几年来又开始阅读，写作的习惯却一直没有培养起来。这中间也有几次尝试过写小说、写散文、写杂文，耗尽心力只得满篇碎语，难说是一篇文章。所以几乎完全放弃写任何东西了。\n读《百分百女孩》和《破碎故事之心》，那种感动涌上来的瞬间，我知道我还是那个“文学青年”，而且永远是。\n我一度很喜欢《大话西游》这部电影。不能免俗地引用女主角那句很悲伤的台词:\n “我的意中人是个盖世英雄，我知道有一天，他会在一个万众瞩目的情况下出现，身披金甲圣衣，脚踏七色云彩来娶我。”\n 我被这句话打动，但我知道就像我没法给哪位姑娘真的抄一辈子诗一样，我也没法脚踏七彩祥云做盖世英雄。也正因为如此，我知道我自己不是一个单纯的文学青年。\n所以我划了这么一块田地，作为我的文学家园。\n 很遗憾，网上完全搜不到这首诗歌的内容，是一首很美的诗 \u0026#x21a9;\u0026#xfe0e;\n   ","description":"一个文学青年的自白","id":0,"section":"essays","tags":["碎语","题辞"],"title":"九月记事","uri":"https://ijoker.me/zh/essays/something-happened-sepetember/"},{"content":"相逢何必曾相识。\n","description":"联系页","id":4,"section":"","tags":null,"title":"Contact","uri":"https://ijoker.me/zh/contact/"},{"content":" 生于早春 浪漫主义诗人1  浪漫主义农民2 浪漫主义程序员3 不是一个有趣的人4 联系方式:常年混迹一个叫V2EX的小论坛5   曾有位朋友问过我一个“三个词定义自己”的问题，记得不差的话当时是随便找三个词搪塞过去了，因为是搪塞，是哪三个词已全无半点印象。\n“名，万物之始也”。下定义是一件很难的事情，这事给我的感觉就像用离散的点去拟合一条平滑的曲线，想想都觉得是在痴人说梦。可朋友的道理在于“认识你自己”，也绝对是人生一桩课题。\n今天想起那位朋友，算来四年过去了，他倒未必还记得有此一人有此一问，我也不妨在此给出一个诚意的答复：“浪漫主义”。\n三个词我只找到一个，不过世间的好多事情，岂不都是答非所问，自言自语么。\n   浪漫主义（Romanticism） 是开始于18世界德国的艺术、文学及文化运动，发生于1790年工业革命开始前夜。浪漫主义注重以强烈的情感作为美学经验的来源。浪漫主义是对于启蒙时代以来贵族和专制政治文化的颠覆，以艺术和文学反抗对于自然的人为理性化。\n\u0026mdash;维基百科6    浪漫主义既不是随兴的取材，也不是强调完全的精确，而是位于两者的中间点，随着感觉而走。\n\u0026ndash; 波德莱尔6     如果会背诗也算诗人的话 \u0026#x21a9;\u0026#xfe0e;\n 需要从头再学，但有深厚家传 \u0026#x21a9;\u0026#xfe0e;\n 平常主要写HelloWorld，梦里在创造伟大的代码 \u0026#x21a9;\u0026#xfe0e;\n 或者不是一个“一直”有趣的人，偶尔有趣 \u0026#x21a9;\u0026#xfe0e;\n 相逢何必曾相识 \u0026#x21a9;\u0026#xfe0e;\n 以上全部是现查的，本人并没有那么多知识储备，波德莱尔其人我也没听过 \u0026#x21a9;\u0026#xfe0e;\n   ","description":"一个浪漫主义者的自白","id":5,"section":"","tags":null,"title":"自定义","uri":"https://ijoker.me/zh/about/"}]